cryptg/__init__.py
cryptg/cryptg.cpython-310-x86_64-linux-gnu.so
cryptg_binary-0.3.1.dist-info/LICENSE.txt
cryptg_binary-0.3.1.dist-info/METADATA
cryptg_binary-0.3.1.dist-info/WHEEL
cryptg_binary-0.3.1.dist-info/top_level.txt
cryptg_binary-0.3.1.dist-info/RECORD
